drawportlab/SheetFormat.py
drawportlab/__init__.py
drawportlab/draw.py
drawportlab/shapes.py
drawportlab-0.5.0.dist-info/METADATA
drawportlab-0.5.0.dist-info/WHEEL
drawportlab-0.5.0.dist-info/top_level.txt
drawportlab-0.5.0.dist-info/RECORD
