Metadata-Version: 2.1
Name: drawportlab
Version: 0.5.0
Summary: Addon to reportlab with focus on mechanical drawings
Home-page: UNKNOWN
Author: Morey_W.
License: UNKNOWN
Platform: UNKNOWN
Requires-Dist: reportlab >=4.0.0
